gpx/__init__.py
gpx/_regressor.py
gpx/gpx_regressor_module.py
gpx/kernel_utils.py
gpx/tensor_utils.py
pytorch_gpx-0.1.dist-info/LICENSE.txt
pytorch_gpx-0.1.dist-info/METADATA
pytorch_gpx-0.1.dist-info/WHEEL
pytorch_gpx-0.1.dist-info/top_level.txt
pytorch_gpx-0.1.dist-info/RECORD
